LICENSE
README.md
setup.cfg
setup.py
SferumBridge/__init__.py
SferumBridge/md.py
SferumBridge/sferum_api.py
SferumBridge.egg-info/PKG-INFO
SferumBridge.egg-info/SOURCES.txt
SferumBridge.egg-info/dependency_links.txt
SferumBridge.egg-info/requires.txt
SferumBridge.egg-info/top_level.txt