Metadata-Version: 2.4
Name: SferumBridge
Version: 1.1.0
Summary: An API wrapper for Sferum.
Home-page: https://github.com/Sharkow1743/SferumAPI
Download-URL: https://github.com/Sharkow1743/SferumAPI/archive/vv1.1.0.zip
Author: Sharkow1743
Author-email: sharkow1743@gmail.com
Classifier: Programming Language :: Python :: 3
Classifier: License :: OSI Approved :: MIT License
Classifier: Operating System :: OS Independent
Requires-Python: >=3.6
License-File: LICENSE
Requires-Dist: requests>=2.25.1
Dynamic: author
Dynamic: author-email
Dynamic: classifier
Dynamic: description
Dynamic: description-content-type
Dynamic: download-url
Dynamic: home-page
Dynamic: license-file
Dynamic: requires-dist
Dynamic: requires-python
Dynamic: summary
